flint_python-0.1.7.dist-info/licenses/LICENSE
pyflint/__init__.py
pyflint/generated/__init__.py
pyflint/generated/message_pool.py
pyflint/generated/py.typed
pyflint/k8s/K8SStack.py
pyflint/k8s/output.py
pyflint/k8s/secret.py
pyflint/k8s/service.py
flint_python-0.1.7.dist-info/METADATA
flint_python-0.1.7.dist-info/WHEEL
flint_python-0.1.7.dist-info/top_level.txt
flint_python-0.1.7.dist-info/RECORD
