Metadata-Version: 2.4
Name: flint-python
Version: 0.1.7
Summary: A BLAZING FAST Cloud Development Kit with a chance of meatballs.
Author: Yoav Oren
License: This is free and unencumbered software released into the public domain.
Requires-Python: >=3.8
License-File: LICENSE
Requires-Dist: typeguard
Requires-Dist: betterproto2
Dynamic: license-file
